{"cameraMode":{"drawMode":0,"name":"Shaded","section":"Shading Mode"},"sceneLighting":true,"audioPlay":false,"sceneViewState":{"showFog":true,"showMaterialUpdate":false,"showSkybox":true,"showFlares":true,"showImageEffects":true,"showParticleSystems":true},"in2DMode":false,"pivot":{"x":13.202545166015625,"y":1.8232390880584717,"z":11.183700561523438},"rotation":{"x":0.011501900851726532,"y":0.08990465104579926,"z":0.0004845901858061552,"w":0.9962101578712463},"size":15.419113159179688,"orthographic":false}